LICENSE
MANIFEST.in
README.md
pyproject.toml
setup.cfg
setup.py
pretix_monetico/__init__.py
pretix_monetico/apps.py
pretix_monetico/moneticoPaiementEpt.py
pretix_monetico/payment.py
pretix_monetico/signals.py
pretix_monetico/urls.py
pretix_monetico/views.py
pretix_monetico.egg-info/PKG-INFO
pretix_monetico.egg-info/SOURCES.txt
pretix_monetico.egg-info/dependency_links.txt
pretix_monetico.egg-info/entry_points.txt
pretix_monetico.egg-info/top_level.txt
pretix_monetico/locale/django.pot
pretix_monetico/locale/de/LC_MESSAGES/django.po
pretix_monetico/locale/es/LC_MESSAGES/django.po
pretix_monetico/locale/fr/LC_MESSAGES/django.po
pretix_monetico/locale/it/LC_MESSAGES/django.po
pretix_monetico/locale/pt/LC_MESSAGES/django.po
pretix_monetico/static/pretix_monetico/.gitkeep
pretix_monetico/static/pretix_monetico/monetico-logo.ai
pretix_monetico/static/pretix_monetico/monetico-logo.png
pretix_monetico/static/pretix_monetico/monetico-logo.svg
pretix_monetico/templates/pretix_monetico/.gitkeep
pretix_monetico/templates/pretix_monetico/checkout_payment_form.html
pretix_monetico/templates/pretix_monetico/control.html
pretix_monetico/templates/pretix_monetico/pending.html
pretix_monetico/templates/pretix_monetico/prepare.html
pretix_monetico/templates/pretix_monetico/redirect.html
pretix_monetico/templates/pretix_monetico/email/order_pending.txt
tests/test_main.py