Metadata-Version: 2.1
Name: pretix-monetico
Version: 0.9.4
Summary: plugin for accepting Monetico payments
Author-email: Ronan LE MEILLAT <ronan@highcanfly.club>
Maintainer-email: Ronan LE MEILLAT <ronan@highcanfly.club>
License: Apache
Project-URL: homepage, https://github.com/highcanfly-club/pretix-monetico.git
Project-URL: repository, https://github.com/highcanfly-club/pretix-monetico.git
Keywords: pretix
License-File: LICENSE
